{"nodes": [{"id": "eeg_sensor", "label": "eeg_sensor.rs", "file_type": "code", "source_file": "src\\eeg_sensor.rs", "source_location": "L1"}, {"id": "eeg_sensor_eegsensor", "label": "EegSensor", "file_type": "code", "source_file": "src\\eeg_sensor.rs", "source_location": "L4"}, {"id": "eeg_sensor_eegdata", "label": "EegData", "file_type": "code", "source_file": "src\\eeg_sensor.rs", "source_location": "L6"}, {"id": "eeg_sensor_eegsensor_new", "label": ".new()", "file_type": "code", "source_file": "src\\eeg_sensor.rs", "source_location": "L12"}, {"id": "eeg_sensor_eegsensor_parse_packet", "label": ".parse_packet()", "file_type": "code", "source_file": "src\\eeg_sensor.rs", "source_location": "L19"}, {"id": "eeg_sensor_eegsensor_log", "label": ".log()", "file_type": "code", "source_file": "src\\eeg_sensor.rs", "source_location": "L29"}], "edges": [{"source": "eeg_sensor", "target": "logwriter", "relation": "imports_from", "confidence": "EXTRACTED", "source_file": "src\\eeg_sensor.rs", "source_location": "L1", "weight": 1.0}, {"source": "eeg_sensor", "target": "write", "relation": "imports_from", "confidence": "EXTRACTED", "source_file": "src\\eeg_sensor.rs", "source_location": "L2", "weight": 1.0}, {"source": "eeg_sensor", "target": "eeg_sensor_eegsensor", "relation": "contains", "confidence": "EXTRACTED", "source_file": "src\\eeg_sensor.rs", "source_location": "L4", "weight": 1.0}, {"source": "eeg_sensor", "target": "eeg_sensor_eegdata", "relation": "contains", "confidence": "EXTRACTED", "source_file": "src\\eeg_sensor.rs", "source_location": "L6", "weight": 1.0}, {"source": "eeg_sensor_eegsensor", "target": "eeg_sensor_eegsensor_new", "relation": "method", "confidence": "EXTRACTED", "source_file": "src\\eeg_sensor.rs", "source_location": "L12", "weight": 1.0}, {"source": "eeg_sensor_eegsensor", "target": "eeg_sensor_eegsensor_parse_packet", "relation": "method", "confidence": "EXTRACTED", "source_file": "src\\eeg_sensor.rs", "source_location": "L19", "weight": 1.0}, {"source": "eeg_sensor_eegsensor", "target": "eeg_sensor_eegsensor_log", "relation": "method", "confidence": "EXTRACTED", "source_file": "src\\eeg_sensor.rs", "source_location": "L29", "weight": 1.0}]}